dash_kbar/DashKbar.py
dash_kbar/__init__.py
dash_kbar/_imports_.py
dash_kbar/dash_kbar.min.js
dash_kbar/dash_kbar.min.js.map
dash_kbar/metadata.json
dash_kbar/package-info.json
dash_kbar-0.4.0.dist-info/LICENSE
dash_kbar-0.4.0.dist-info/METADATA
dash_kbar-0.4.0.dist-info/WHEEL
dash_kbar-0.4.0.dist-info/top_level.txt
dash_kbar-0.4.0.dist-info/RECORD
