Metadata-Version: 2.1
Name: dash_kbar
Version: 0.4.0
Summary: cmd + k interface for dash applications
Author: Najeem Muhammed <najeem@gmail.com>
License: MIT
Classifier: Framework :: Dash
License-File: LICENSE
